MANIFEST.in
README.md
setup.py
nc5ng/core/__init__.py
nc5ng/core/bicubic.pyf
nc5ng/core/bilin.pyf
nc5ng/core/biquad.pyf
nc5ng/core/bwplotcv.pyf
nc5ng/core/bwplotvc.pyf
nc5ng/core/coplot.pyf
nc5ng/core/coplotwcv.pyf
nc5ng/core/cpt.pyf
nc5ng/core/cpt2.pyf
nc5ng/core/cubterp.pyf
nc5ng/core/getgridbounds.pyf
nc5ng/core/getmag.pyf
nc5ng/core/getmapbounds.pyf
nc5ng/core/gridstats.pyf
nc5ng/core/indexxd.pyf
nc5ng/core/indexxi.pyf
nc5ng/core/iselect2.pyf
nc5ng/core/onzd.pyf
nc5ng/core/onzd2.pyf
nc5ng/core/plotcoast.pyf
nc5ng/core/qterp.pyf
nc5ng/core/select2_dbl.pyf
nc5ng/core/select2_mod.pyf
nc5ng/core/vecstats.pyf
nc5ng/nc5data/__init__.py
nc5ng/nc5data/conversion.py
nc5ng/nc5data/nadcon5_files.py
nc5ng/nc5data/nadcon5_input.py
nc5ng/nc5data/nadcon5_output.py
nc5ng/nc5data/nadcon5_types.py
nc5ng/nc5data/services.py
nc5ng/nc5data/utils.py
nc5ng/nc5data/data/gmtdefaults4
nc5ng/nc5data/data/Boundaries/.gmtcommands4
nc5ng/nc5data/data/Boundaries/.gmtdefaults4
nc5ng/nc5data/data/Boundaries/AK_Adak.gmt
nc5ng/nc5data/data/Boundaries/AK_Agattu.gmt
nc5ng/nc5data/data/Boundaries/AK_Amchitka.gmt
nc5ng/nc5data/data/Boundaries/AK_Amlia.gmt
nc5ng/nc5data/data/Boundaries/AK_Amukta.gmt
nc5ng/nc5data/data/Boundaries/AK_Andreanof.gmt
nc5ng/nc5data/data/Boundaries/AK_Atka.gmt
nc5ng/nc5data/data/Boundaries/AK_Attu.gmt
nc5ng/nc5data/data/Boundaries/AK_Buldir.gmt
nc5ng/nc5data/data/Boundaries/AK_Carlisle.gmt
nc5ng/nc5data/data/Boundaries/AK_Chagulak.gmt
nc5ng/nc5data/data/Boundaries/AK_Chugul.gmt
nc5ng/nc5data/data/Boundaries/AK_Fenimore.gmt
nc5ng/nc5data/data/Boundaries/AK_FourMountains.gmt
nc5ng/nc5data/data/Boundaries/AK_GreatSitkin.gmt
nc5ng/nc5data/data/Boundaries/AK_Hall.gmt
nc5ng/nc5data/data/Boundaries/AK_Herbert.gmt
nc5ng/nc5data/data/Boundaries/AK_Igitkin.gmt
nc5ng/nc5data/data/Boundaries/AK_Ikiginak.gmt
nc5ng/nc5data/data/Boundaries/AK_Kagalaska.gmt
nc5ng/nc5data/data/Boundaries/AK_Kagami.gmt
nc5ng/nc5data/data/Boundaries/AK_Kanaga.gmt
nc5ng/nc5data/data/Boundaries/AK_Kasatochi.gmt
nc5ng_core.egg-info/PKG-INFO
nc5ng_core.egg-info/SOURCES.txt
nc5ng_core.egg-info/dependency_links.txt
nc5ng_core.egg-info/requires.txt
nc5ng_core.egg-info/top_level.txt
