Metadata-Version: 1.1
Name: nc5ng-core
Version: 0.0.4
Summary: Python Package and Wrapper for the NADCON5 Datum Transformation Data and Utilities
Home-page: https://nc5ng.org
Author: Andrey Shmakov
Author-email: akshmakov@gmail.com
License: UNKNOWN
Download-URL: https://github.com/nc5ng/nadcon5-ng
Platform: UNKNOWN
